lambdatest_sdk_utils/__init__.py
lambdatest_sdk_utils/constants.py
lambdatest_sdk_utils/logger.py
lambdatest_sdk_utils/rest.py
lambdatest_sdk_utils/version.py
lambdatest_sdk_utils-1.0.4.dist-info/METADATA
lambdatest_sdk_utils-1.0.4.dist-info/WHEEL
lambdatest_sdk_utils-1.0.4.dist-info/top_level.txt
lambdatest_sdk_utils-1.0.4.dist-info/RECORD
